[
  {
      "name": "Project Paper Format and Style Guidelines",
      "link": "https://drive.google.com/file/d/1Lq8Djqxv5n2Br0TjjoWQKNwz1ev1HFFZ/preview"
  },
  {
      "name": "School/College Management System (SCMS)",
      "link": "https://drive.google.com/file/d/1kOMsC8UQJnGRl17fifQaeFnZiIZAe-rV/preview"
  },
  {
      "name": "Multi-Tenant E-Commerce Platform",
      "link": "https://drive.google.com/file/d/1a0B_DNlB0YeJBN-t66mxForSjy9byjYF/preview"
  },
  {
      "name": "Book 3",
      "link": "path/to/book2.pdf"
  },
  {
      "name": "Book 3",
      "link": "path/to/book2.pdf"
  }
]